odoo/addons/base_name_search_improved/README.rst
odoo/addons/base_name_search_improved/__init__.py
odoo/addons/base_name_search_improved/__manifest__.py
odoo/addons/base_name_search_improved/hooks.py
odoo/addons/base_name_search_improved/i18n/base_name_search_improved.pot
odoo/addons/base_name_search_improved/i18n/ca.po
odoo/addons/base_name_search_improved/i18n/de.po
odoo/addons/base_name_search_improved/i18n/es.po
odoo/addons/base_name_search_improved/i18n/es_ES.po
odoo/addons/base_name_search_improved/i18n/eu.po
odoo/addons/base_name_search_improved/i18n/fi.po
odoo/addons/base_name_search_improved/i18n/fr.po
odoo/addons/base_name_search_improved/i18n/hr.po
odoo/addons/base_name_search_improved/i18n/hr_HR.po
odoo/addons/base_name_search_improved/i18n/it.po
odoo/addons/base_name_search_improved/i18n/nb_NO.po
odoo/addons/base_name_search_improved/i18n/nl.po
odoo/addons/base_name_search_improved/i18n/pt_BR.po
odoo/addons/base_name_search_improved/i18n/sl.po
odoo/addons/base_name_search_improved/i18n/tr.po
odoo/addons/base_name_search_improved/i18n/tr_TR.po
odoo/addons/base_name_search_improved/i18n/zh_CN.po
odoo/addons/base_name_search_improved/images/image0.png
odoo/addons/base_name_search_improved/images/image1.png
odoo/addons/base_name_search_improved/images/image2.png
odoo/addons/base_name_search_improved/models/__init__.py
odoo/addons/base_name_search_improved/models/ir_model.py
odoo/addons/base_name_search_improved/readme/CONFIGURE.rst
odoo/addons/base_name_search_improved/readme/CONTRIBUTORS.rst
odoo/addons/base_name_search_improved/readme/CREDITS.rst
odoo/addons/base_name_search_improved/readme/DESCRIPTION.rst
odoo/addons/base_name_search_improved/readme/ROADMAP.rst
odoo/addons/base_name_search_improved/readme/USAGE.rst
odoo/addons/base_name_search_improved/static/description/icon.png
odoo/addons/base_name_search_improved/static/description/index.html
odoo/addons/base_name_search_improved/tests/__init__.py
odoo14_addon_base_name_search_improved-14.0.1.1.2.dist-info/METADATA
odoo14_addon_base_name_search_improved-14.0.1.1.2.dist-info/WHEEL
odoo14_addon_base_name_search_improved-14.0.1.1.2.dist-info/top_level.txt
odoo14_addon_base_name_search_improved-14.0.1.1.2.dist-info/RECORD
