Metadata-Version: 2.1
Name: odoo14-addon-base-name-search-improved
Version: 14.0.1.1.2
Summary: Friendlier search when typing in relation fields
Home-page: https://github.com/OCA/server-tools
Author: Daniel Reis, Odoo Community Association (OCA), ADHOC SA
Author-email: support@odoo-community.org
License: AGPL-3
Platform: UNKNOWN
Classifier: Programming Language :: Python
Classifier: Framework :: Odoo
Classifier: Framework :: Odoo :: 14.0
Classifier: License :: OSI Approved :: GNU Affero General Public License v3
Requires-Python: >=3.6
Requires-Dist: odoo <14.1dev,>=14.0a
